az_auth/__init__.py
az_auth/auth.py
az_auth-0.1.2.dist-info/METADATA
az_auth-0.1.2.dist-info/WHEEL
az_auth-0.1.2.dist-info/top_level.txt
az_auth-0.1.2.dist-info/RECORD
