Metadata-Version: 2.4
Name: az-auth
Version: 0.1.2
Summary: Azure authentication utilities for Microsoft Graph and ARM APIs
Author-email: Karim El-Melhaoui <karim@o3c.no>
License: MIT
Project-URL: Homepage, https://github.com/karimelmel/
Project-URL: Repository, https://github.com/karimelmel/az-auth
Keywords: azure,authentication,graph,arm,identity
Requires-Python: >=3.8
Requires-Dist: azure-identity>=1.10.0
